{
  "task_id": "SMART-001",
  "title": "Task 3: 实现窗口过滤逻辑 (AC: 2, 3)",
  "verdict": "pass",
  "score": 95,
  "summary": "实现正确完成了 AC2 和 AC3 的所有要求。代码质量高，测试覆盖全面（32个测试全部通过），无安全漏洞，符合项目规范。仅发现一个微小的测试函数命名拼写错误。",
  "issues": [
    {
      "severity": "low",
      "file": "src-tauri/src/window_info/mod.rs",
      "line": 447,
      "description": "测试函数名拼写错误：'should_capture_by_window_whitelist_allls_all_when_empty' 中 'allls' 应为 'allows'",
      "suggestion": "重命名为 'should_capture_by_window_whitelist_allows_all_when_empty'"
    }
  ],
  "strengths": [
    "代码注释清晰，明确标注了 AC2/AC3 对应关系",
    "测试覆盖全面，包含边界测试（空标题、空进程名、unicode、大小写）",
    "函数设计简洁，符合单一职责原则",
    "matches_any 函数正确处理空文本和空模式列表的边界情况",
    "should_capture_by_window 正确实现白名单优先级逻辑（AC3）",
    "32个测试全部通过，clippy 无警告，格式检查通过"
  ],
  "recommendation": "approve"
}